LICENSE
MANIFEST.in
README.rst
requirements.txt
setup.py
rest_api_blueprint.egg-info/PKG-INFO
rest_api_blueprint.egg-info/SOURCES.txt
rest_api_blueprint.egg-info/dependency_links.txt
rest_api_blueprint.egg-info/not-zip-safe
rest_api_blueprint.egg-info/requires.txt
rest_api_blueprint.egg-info/top_level.txt
restapiblueprint/__init__.py
restapiblueprint/database.py
restapiblueprint/views.py
restapiblueprint/blueprints/__init__.py
restapiblueprint/blueprints/counter.py
restapiblueprint/blueprints/people.py
restapiblueprint/blueprints/private.py
restapiblueprint/features/__init__.py
restapiblueprint/features/environment.py
restapiblueprint/features/steps/__init__.py
restapiblueprint/features/steps/rest.py
restapiblueprint/lib/__init__.py
restapiblueprint/lib/oauth.py
restapiblueprint/lib/oauth_test.py
restapiblueprint/static/emptydirectory
restapiblueprint/static/apidocs/.buildinfo
restapiblueprint/static/apidocs/index.html
restapiblueprint/static/apidocs/objects.inv
restapiblueprint/static/apidocs/people.html
restapiblueprint/static/apidocs/search.html
restapiblueprint/static/apidocs/searchindex.js
restapiblueprint/static/apidocs/_sources/index.txt
restapiblueprint/static/apidocs/_sources/people.txt
restapiblueprint/static/apidocs/_static/ajax-loader.gif
restapiblueprint/static/apidocs/_static/ansi.css
restapiblueprint/static/apidocs/_static/basic.css
restapiblueprint/static/apidocs/_static/comment-bright.png
restapiblueprint/static/apidocs/_static/comment-close.png
restapiblueprint/static/apidocs/_static/comment.png
restapiblueprint/static/apidocs/_static/contents.png
restapiblueprint/static/apidocs/_static/doctools.js
restapiblueprint/static/apidocs/_static/down-pressed.png
restapiblueprint/static/apidocs/_static/down.png
restapiblueprint/static/apidocs/_static/file.png
restapiblueprint/static/apidocs/_static/jquery.js
restapiblueprint/static/apidocs/_static/minus.png
restapiblueprint/static/apidocs/_static/navigation.png
restapiblueprint/static/apidocs/_static/plus.png
restapiblueprint/static/apidocs/_static/pygments.css
restapiblueprint/static/apidocs/_static/searchtools.js
restapiblueprint/static/apidocs/_static/sphinxdoc.css
restapiblueprint/static/apidocs/_static/underscore.js
