Metadata-Version: 1.1
Name: rest-api-blueprint
Version: 0.1
Summary: Pedagogical blueprint of a REST API in Flask.
Home-page: http://bitbucket.org/tcorbettclark/rest-api-blueprint/
Author: Timothy Corbett-Clark
Author-email: timothy@corbettclark.com
License: This code is made available under the BSD 2-Clause License
